{"english-450k": {"roll-out": 0.0, "sfR": 0.11369548401129392, "dsfb": 0.0, "roll-in": 0.0, "dsfb-red": 0.0, "oneh-in": 0.0, "sfT": 0.8861507418869544, "dsfb-alt": 0.0, "alternate": 0.0, "sft": 0.0, "oneh-out": 0.0, "unknown": 0.00015377410175167997, "redirect": 0.0, "bad-redirect": 0.0, "sfb": 0.0}, "shai": {"roll-out": 0.0, "sfR": 0.09823378925716947, "dsfb": 0.0, "roll-in": 0.0, "dsfb-red": 0.00044631232093553664, "oneh-in": 0.0, "sfT": 0.8797399735511744, "dsfb-alt": 0.0, "alternate": 0.0, "sft": 0.0, "oneh-out": 0.0, "unknown": 0.020466005735016952, "redirect": 0.0, "bad-redirect": 0.0, "sfb": 0.0011139191357036542}, "tr-quotes": {"roll-out": 0.0, "sfR": 0.09677191928064538, "dsfb": 0.0, "roll-in": 0.0, "dsfb-red": 9.015048195834585e-05, "oneh-in": 0.0, "sfT": 0.8896904833452763, "dsfb-alt": 0.0, "alternate": 0.0, "sft": 0.0, "oneh-out": 0.0, "unknown": 0.013240563093779616, "redirect": 0.0, "bad-redirect": 0.0, "sfb": 0.0002068837983403065}, "gutenberg": {"roll-out": 0.0, "sfR": 0.09863878308844841, "dsfb": 0.0, "roll-in": 0.0, "dsfb-red": 7.028104461501332e-05, "oneh-in": 0.0, "sfT": 0.8687466446010708, "dsfb-alt": 0.0, "alternate": 0.0, "sft": 0.0, "oneh-out": 0.0, "unknown": 0.032238729743051746, "redirect": 0.0, "bad-redirect": 0.0, "sfb": 0.0003055615228140606}, "english-200": {"roll-out": 0.0, "sfR": 0.10690423162583519, "dsfb": 0.0, "roll-in": 0.0, "dsfb-red": 0.0, "oneh-in": 0.0, "sfT": 0.8930957683741648, "dsfb-alt": 0.0, "alternate": 0.0, "sft": 0.0, "oneh-out": 0.0, "unknown": 0.0, "redirect": 0.0, "bad-redirect": 0.0, "sfb": 0.0}, "monkeyracer": {"roll-out": 0.0, "sfR": 0.09690789370786869, "dsfb": 0.0, "roll-in": 0.0, "dsfb-red": 8.504465333062233e-05, "oneh-in": 0.0, "sfT": 0.8899326680951561, "dsfb-alt": 0.0, "alternate": 0.0, "sft": 0.0, "oneh-out": 0.0, "unknown": 0.012881821167711966, "redirect": 0.0, "bad-redirect": 0.0, "sfb": 0.00019257237593255861}, "chained-bigrams": {"roll-out": 0.0, "sfR": 0.11914286586209158, "dsfb": 0.0, "roll-in": 0.0, "dsfb-red": 0.0003363398304925171, "oneh-in": 0.0, "sfT": 0.8591774997743666, "dsfb-alt": 0.0, "alternate": 0.0, "sft": 0.0, "oneh-out": 0.0, "unknown": 0.02072320855212196, "redirect": 0.0, "bad-redirect": 0.0, "sfb": 0.000620085980927324}, "english-5k": {"roll-out": 0.0, "sfR": 0.10644211224955408, "dsfb": 0.0, "roll-in": 0.0, "dsfb-red": 0.0, "oneh-in": 0.0, "sfT": 0.8914008379308914, "dsfb-alt": 0.0, "alternate": 0.0, "sft": 0.0, "oneh-out": 0.0, "unknown": 0.002157049819554486, "redirect": 0.0, "bad-redirect": 0.0, "sfb": 0.0}, "mt-quotes": {"roll-out": 0.0, "sfR": 0.0964592223377679, "dsfb": 0.0, "roll-in": 0.0, "dsfb-red": 2.689425180191487e-05, "oneh-in": 0.0, "sfT": 0.8956368558826694, "dsfb-alt": 0.0, "alternate": 0.0, "sft": 0.0, "oneh-out": 0.0, "unknown": 0.007815768398656484, "redirect": 0.0, "bad-redirect": 0.0, "sfb": 6.125912910436165e-05}, "wordle": {"roll-out": 0.0, "sfR": 0.13138112868843263, "dsfb": 0.0, "roll-in": 0.0, "dsfb-red": 0.0, "oneh-in": 0.0, "sfT": 0.8686188713115673, "dsfb-alt": 0.0, "alternate": 0.0, "sft": 0.0, "oneh-out": 0.0, "unknown": 0.0, "redirect": 0.0, "bad-redirect": 0.0, "sfb": 0.0}, "english-1k": {"roll-out": 0.0, "sfR": 0.10832745236414962, "dsfb": 0.0, "roll-in": 0.0, "dsfb-red": 0.0, "oneh-in": 0.0, "sfT": 0.8916725476358504, "dsfb-alt": 0.0, "alternate": 0.0, "sft": 0.0, "oneh-out": 0.0, "unknown": 0.0, "redirect": 0.0, "bad-redirect": 0.0, "sfb": 0.0}, "english-10k": {"roll-out": 0.0, "sfR": 0.10567144593890508, "dsfb": 0.0, "roll-in": 0.0, "dsfb-red": 0.0, "oneh-in": 0.0, "sfT": 0.8943285540610949, "dsfb-alt": 0.0, "alternate": 0.0, "sft": 0.0, "oneh-out": 0.0, "unknown": 0.0, "redirect": 0.0, "bad-redirect": 0.0, "sfb": 0.0}, "reddit": {"roll-out": 0.0, "sfR": 0.10397777127267367, "dsfb": 0.0, "roll-in": 0.0, "dsfb-red": 0.0004740235648332574, "oneh-in": 0.0, "sfT": 0.859432628815576, "dsfb-alt": 0.0, "alternate": 0.0, "sft": 0.0, "oneh-out": 0.0, "unknown": 0.034785426144562766, "redirect": 0.0, "bad-redirect": 0.0, "sfb": 0.0013301502023543108}, "akl": {"roll-out": 0.0, "sfR": 0.13064861186637447, "dsfb": 0.0, "roll-in": 0.0, "dsfb-red": 0.0001749298236151457, "oneh-in": 0.0, "sfT": 0.7386240084314198, "dsfb-alt": 0.0, "alternate": 0.0, "sft": 0.0, "oneh-out": 0.0, "unknown": 0.1292719289790846, "redirect": 0.0, "bad-redirect": 0.0, "sfb": 0.0012805208995059541}, "french": {"roll-out": 0.0, "sfR": 0.10898279115633469, "dsfb": 0.0, "roll-in": 0.0, "dsfb-red": 0.0006644295486018552, "oneh-in": 0.0, "sfT": 0.7344527283523186, "dsfb-alt": 0.0, "alternate": 0.0, "sft": 0.0, "oneh-out": 0.0, "unknown": 0.154532958194094, "redirect": 0.0, "bad-redirect": 0.0, "sfb": 0.0013670927486509118}, "keymash": {"roll-out": 0.0, "sfR": 0.099723742164827, "dsfb": 0.0, "roll-in": 0.0, "dsfb-red": 7.79925537635512e-05, "oneh-in": 0.0, "sfT": 0.8880642658643012, "dsfb-alt": 0.0, "alternate": 0.0, "sft": 0.0, "oneh-out": 0.0, "unknown": 0.012019063022088312, "redirect": 0.0, "bad-redirect": 0.0, "sfb": 0.0001149363950199702}, "movie": {"roll-out": 0.0, "sfR": 0.11567713207251198, "dsfb": 0.0, "roll-in": 0.0, "dsfb-red": 0.0, "oneh-in": 0.0, "sfT": 0.8541651176504417, "dsfb-alt": 0.0, "alternate": 0.0, "sft": 0.0, "oneh-out": 0.0, "unknown": 0.030154855124597493, "redirect": 0.0, "bad-redirect": 0.0, "sfb": 2.895152448858119e-06}, "dutch": {"roll-out": 0.0, "sfR": 0.18880787437283908, "dsfb": 0.0, "roll-in": 0.0, "dsfb-red": 0.00042320260553088256, "oneh-in": 0.0, "sfT": 0.7396095440453644, "dsfb-alt": 0.0, "alternate": 0.0, "sft": 0.0, "oneh-out": 0.0, "unknown": 0.06994293596457937, "redirect": 0.0, "bad-redirect": 0.0, "sfb": 0.0012164430116863233}}